npdep_server/__init__.py
npdep_server/__main__.py
npdep_server/args/Args.py
npdep_server/args/__init__.py
npdep_server/logger/Logger.py
npdep_server/logger/__init__.py
npdep_server/output/Output.py
npdep_server/output/__init__.py
npdep_server/util/Util.py
npdep_server/util/__init__.py
npdep_server-0.1.0.dist-info/METADATA
npdep_server-0.1.0.dist-info/WHEEL
npdep_server-0.1.0.dist-info/entry_points.txt
npdep_server-0.1.0.dist-info/top_level.txt
npdep_server-0.1.0.dist-info/RECORD
