Metadata-Version: 2.1
Name: npdep_server
Version: 0.1.0
Summary: Network Protocol Data Exfiltration Project Server - A modular approach for data exfiltration
Home-page: https://github.com/npdep/npdep-server
Author: npdep
Classifier: Operating System :: OS Independent 
Classifier: Programming Language :: Python :: 3 
Requires-Dist: npdep-common
